LICENSE
README.md
setup.py
pycloudkit/__init__.py
pycloudkit.egg-info/PKG-INFO
pycloudkit.egg-info/SOURCES.txt
pycloudkit.egg-info/dependency_links.txt
pycloudkit.egg-info/top_level.txt
pycloudkit/cloud/__init__.py
pycloudkit/cloud/src/cloud.py
pycloudkit/cloud/src/cloudtypes.py
pycloudkit/cloud/src/utils.py
pycloudkit/src/client.py
pycloudkit/src/filemanager.py
pycloudkit/src/request.py
pycloudkit/src/server.py
pycloudkit/src/types.py
pycloudkit/src/utils.py
pycloudkit/cloud/__init__.py
pycloudkit/cloud/src/cloud.py
pycloudkit/cloud/src/cloudtypes.py
pycloudkit/cloud/src/utils.py
pycloudkit/src/client.py
pycloudkit/src/request.py
pycloudkit/src/server.py
pycloudkit/src/types.py
pycloudkit/src/utils.py