Metadata-Version: 2.1
Name: pycloudkit
Version: 1.0.3
Summary: A library for creating and working with cloud databases
Home-page: https://github.com/professionsalincpp/pyserver
Author: griguchaev
Author-email: griguchaev@yandex.ru
Classifier: Programming Language :: Python :: 3
Classifier: License :: OSI Approved :: MIT License
Classifier: Operating System :: OS Independent
Requires-Python: >=3.6
License-File: LICENSE
